[
  {
    "obj_id": "0",
    "obj_type": "Vehicle",
    "psr": {
      "position": {
        "x": 6.016989231109619,
        "y": 3.830613136291504,
        "z": 0.8106444478034973
      },
      "rotation": {
        "x": 0,
        "y": 0,
        "z": 3.1972875595092773
      },
      "scale": {
        "x": 4.488316059112549,
        "y": 1.8997758626937866,
        "z": 1.7605242729187012
      }
    }
  },
  {
    "obj_id": "1",
    "obj_type": "Vehicle",
    "psr": {
      "position": {
        "x": 43.76344299316406,
        "y": 4.678941249847412,
        "z": 1.2613251209259033
      },
      "rotation": {
        "x": 0,
        "y": 0,
        "z": 3.134330987930298
      },
      "scale": {
        "x": 5.616741180419922,
        "y": 2.2801332473754883,
        "z": 2.6392571926116943
      }
    }
  },
  {
    "obj_id": "2",
    "obj_type": "Vehicle",
    "psr": {
      "position": {
        "x": 26.966291427612305,
        "y": 4.3173322677612305,
        "z": 0.6600121855735779
      },
      "rotation": {
        "x": 0,
        "y": 0,
        "z": 3.1686339378356934
      },
      "scale": {
        "x": 4.591803073883057,
        "y": 1.8955305814743042,
        "z": 1.5847922563552856
      }
    }
  },
  {
    "obj_id": "3",
    "obj_type": "Vehicle",
    "psr": {
      "position": {
        "x": 15.650436401367188,
        "y": -2.7068750858306885,
        "z": 0.9298364520072937
      },
      "rotation": {
        "x": 0,
        "y": 0,
        "z": 6.381460666656494
      },
      "scale": {
        "x": 4.830897331237793,
        "y": 2.01607346534729,
        "z": 2.063523292541504
      }
    }
  },
  {
    "obj_id": "4",
    "obj_type": "Cyclist",
    "psr": {
      "position": {
        "x": 11.01157283782959,
        "y": -0.892827570438385,
        "z": 0.7519240975379944
      },
      "rotation": {
        "x": 0,
        "y": 0,
        "z": 3.5256969928741455
      },
      "scale": {
        "x": 2.086441993713379,
        "y": 0.7757836580276489,
        "z": 1.5564333200454712
      }
    }
  },
  {
    "obj_id": "5",
    "obj_type": "Vehicle",
    "psr": {
      "position": {
        "x": 56.28549575805664,
        "y": 1.8762353658676147,
        "z": 0.810509979724884
      },
      "rotation": {
        "x": 0,
        "y": 0,
        "z": 6.363305568695068
      },
      "scale": {
        "x": 4.667025089263916,
        "y": 1.9610553979873657,
        "z": 1.7344694137573242
      }
    }
  },
  {
    "obj_id": "6",
    "obj_type": "Vehicle",
    "psr": {
      "position": {
        "x": 35.92250061035156,
        "y": -3.8453359603881836,
        "z": 1.5107232332229614
      },
      "rotation": {
        "x": 0,
        "y": 0,
        "z": 6.236307144165039
      },
      "scale": {
        "x": 7.140006065368652,
        "y": 2.60591459274292,
        "z": 2.998018503189087
      }
    }
  },
  {
    "obj_id": "7",
    "obj_type": "Cyclist",
    "psr": {
      "position": {
        "x": 11.977317810058594,
        "y": 2.8993921279907227,
        "z": 0.7844552397727966
      },
      "rotation": {
        "x": 0,
        "y": 0,
        "z": 3.0071821212768555
      },
      "scale": {
        "x": 2.0384247303009033,
        "y": 0.7694565653800964,
        "z": 1.5642590522766113
      }
    }
  },
  {
    "obj_id": "8",
    "obj_type": "Pedestrian",
    "psr": {
      "position": {
        "x": 23.278343200683594,
        "y": 6.299194812774658,
        "z": 0.7134526371955872
      },
      "rotation": {
        "x": 0,
        "y": 0,
        "z": 0.6590375304222107
      },
      "scale": {
        "x": 0.7644452452659607,
        "y": 0.6743873953819275,
        "z": 1.7327336072921753
      }
    }
  },
  {
    "obj_id": "9",
    "obj_type": "Pedestrian",
    "psr": {
      "position": {
        "x": 4.6517534255981445,
        "y": 9.335673332214355,
        "z": 0.5400531888008118
      },
      "rotation": {
        "x": 0,
        "y": 0,
        "z": 1.0068652629852295
      },
      "scale": {
        "x": 0.6669037938117981,
        "y": 0.6161173582077026,
        "z": 1.4419379234313965
      }
    }
  },
  {
    "obj_id": "10",
    "obj_type": "Pedestrian",
    "psr": {
      "position": {
        "x": 20.697288513183594,
        "y": 7.955849647521973,
        "z": 0.631999671459198
      },
      "rotation": {
        "x": 0,
        "y": 0,
        "z": 1.5691078901290894
      },
      "scale": {
        "x": 0.6550800204277039,
        "y": 0.6255308985710144,
        "z": 1.7850830554962158
      }
    }
  },
  {
    "obj_id": "11",
    "obj_type": "Pedestrian",
    "psr": {
      "position": {
        "x": 38.37740707397461,
        "y": 8.361166000366211,
        "z": 0.35067111253738403
      },
      "rotation": {
        "x": 0,
        "y": 0,
        "z": 4.759551048278809
      },
      "scale": {
        "x": 0.6608834862709045,
        "y": 0.6481780409812927,
        "z": 1.7537477016448975
      }
    }
  },
  {
    "obj_id": "12",
    "obj_type": "Pedestrian",
    "psr": {
      "position": {
        "x": 44.69025421142578,
        "y": 0.4663863182067871,
        "z": 0.907187283039093
      },
      "rotation": {
        "x": 0,
        "y": 0,
        "z": 4.027549743652344
      },
      "scale": {
        "x": 0.6913632750511169,
        "y": 0.6388587951660156,
        "z": 1.7723077535629272
      }
    }
  },
  {
    "obj_id": "13",
    "obj_type": "Pedestrian",
    "psr": {
      "position": {
        "x": 44.238380432128906,
        "y": 0.3726542592048645,
        "z": 0.8805066347122192
      },
      "rotation": {
        "x": 0,
        "y": 0,
        "z": 3.8432021141052246
      },
      "scale": {
        "x": 0.7426919341087341,
        "y": 0.6771321892738342,
        "z": 1.8369613885879517
      }
    }
  },
  {
    "obj_id": "14",
    "obj_type": "Vehicle",
    "psr": {
      "position": {
        "x": 35.392059326171875,
        "y": 6.083142280578613,
        "z": 0.6143315434455872
      },
      "rotation": {
        "x": 0,
        "y": 0,
        "z": 2.841362953186035
      },
      "scale": {
        "x": 4.312582015991211,
        "y": 1.8857474327087402,
        "z": 1.5705403089523315
      }
    }
  },
  {
    "obj_id": "15",
    "obj_type": "Vehicle",
    "psr": {
      "position": {
        "x": 1.2294420003890991,
        "y": -0.0908544510602951,
        "z": 0.5106073021888733
      },
      "rotation": {
        "x": 0,
        "y": 0,
        "z": 2.9851927757263184
      },
      "scale": {
        "x": 4.345370292663574,
        "y": 1.8627852201461792,
        "z": 1.5545636415481567
      }
    }
  },
  {
    "obj_id": "16",
    "obj_type": "Pedestrian",
    "psr": {
      "position": {
        "x": 31.194711685180664,
        "y": -9.236967086791992,
        "z": 0.7073288559913635
      },
      "rotation": {
        "x": 0,
        "y": 0,
        "z": 0.8114830255508423
      },
      "scale": {
        "x": 0.7945477366447449,
        "y": 0.7310634851455688,
        "z": 1.8222730159759521
      }
    }
  },
  {
    "obj_id": "17",
    "obj_type": "Cyclist",
    "psr": {
      "position": {
        "x": 14.569289207458496,
        "y": 5.979477405548096,
        "z": 0.7317611575126648
      },
      "rotation": {
        "x": 0,
        "y": 0,
        "z": 6.488827228546143
      },
      "scale": {
        "x": 1.9392178058624268,
        "y": 0.7622660994529724,
        "z": 1.6634775400161743
      }
    }
  },
  {
    "obj_id": "18",
    "obj_type": "Pedestrian",
    "psr": {
      "position": {
        "x": 35.25154495239258,
        "y": 11.221756935119629,
        "z": 0.7908698916435242
      },
      "rotation": {
        "x": 0,
        "y": 0,
        "z": 4.920567035675049
      },
      "scale": {
        "x": 0.6318832039833069,
        "y": 0.6356109380722046,
        "z": 1.900161623954773
      }
    }
  },
  {
    "obj_id": "19",
    "obj_type": "Pedestrian",
    "psr": {
      "position": {
        "x": 59.34177780151367,
        "y": -2.599076271057129,
        "z": 0.8206762075424194
      },
      "rotation": {
        "x": 0,
        "y": 0,
        "z": 3.295125961303711
      },
      "scale": {
        "x": 0.6680338382720947,
        "y": 0.6822799444198608,
        "z": 1.8516181707382202
      }
    }
  }
]